LICENSE
MANIFEST.in
README.md
setup.cfg
setup.py
versioneer.py
./.gitattributes
./CODE_OF_CONDUCT.md
./CONTRIBUTING.md
./LICENSE
./MANIFEST.in
./README.md
./setup.cfg
./setup.py
./versioneer.py
./adtypingdecorators/__init__.py
./adtypingdecorators/_version.py
./adtypingdecorators/checker.py
./adtypingdecorators/decorators.py
./adtypingdecorators.egg-info/PKG-INFO
./adtypingdecorators.egg-info/SOURCES.txt
./adtypingdecorators.egg-info/dependency_links.txt
./adtypingdecorators.egg-info/requires.txt
./adtypingdecorators.egg-info/top_level.txt
./tests/__init__.py
./tests/test_adtypingdecorators.py
adtypingdecorators/__init__.py
adtypingdecorators/_version.py
adtypingdecorators/checker.py
adtypingdecorators/decorators.py
adtypingdecorators.egg-info/PKG-INFO
adtypingdecorators.egg-info/SOURCES.txt
adtypingdecorators.egg-info/dependency_links.txt
adtypingdecorators.egg-info/requires.txt
adtypingdecorators.egg-info/top_level.txt
tests/__init__.py
tests/test_adtypingdecorators.py