Metadata-Version: 2.1
Name: adtypingdecorators
Version: 0.1.26
Summary: A Python decorators allowing to check and/or enforce types in functions arguments based on typing hints
Home-page: https://github.com/Advestis/{name}
Author: Advestis
Author-email: pythondev@advestis.com
License: GPLv3
Project-URL: Bug Tracker, https://github.com/Advestis/adtypingdecorators/issues
Project-URL: Documentation, https://advestis.github.io/adtypingdecorators
Project-URL: Source Code, https://github.com/Advestis/adtypingdecorators/
Platform: UNKNOWN
Classifier: Development Status :: 5 - Production/Stable
Classifier: License :: OSI Approved :: GNU General Public License v3 (GPLv3)
Classifier: Operating System :: Unix
Classifier: Programming Language :: Python :: 3.7
Classifier: Programming Language :: Python :: 3.8
Classifier: Programming Language :: Python :: 3.9
Requires-Python: >=3.7
License-File: LICENSE
